deepthought/__init__.py
deepthought/optimize.py
deepthoughts-0.1.2.dist-info/LICENSE.txt
deepthoughts-0.1.2.dist-info/METADATA
deepthoughts-0.1.2.dist-info/WHEEL
deepthoughts-0.1.2.dist-info/top_level.txt
deepthoughts-0.1.2.dist-info/RECORD
